nonebot_plugin_gpt/__init__.py
nonebot_plugin_gpt/api.py
nonebot_plugin_gpt/check.py
nonebot_plugin_gpt/config.py
nonebot_plugin_gpt/source.py
nonebot_plugin_gpt-1.0.3.dist-info/WHEEL
nonebot_plugin_gpt-1.0.3.dist-info/METADATA
nonebot_plugin_gpt-1.0.3.dist-info/licenses/LICENSE
nonebot_plugin_gpt-1.0.3.dist-info/RECORD
