Metadata-Version: 2.1
Name: nonebot-plugin-gpt
Version: 1.0.3
Summary: Nonebot2's plugin of ChatGPT 
License: GPL3
Author-email: nek0us <nekouss@mail.com>
Requires-Python: >=3.10
Requires-Dist: ChatGPTWeb>=0.3.3
Requires-Dist: more_itertools
Requires-Dist: nonebot-plugin-sendmsg-by-bots>=0.2.0
Requires-Dist: nonebot2>=2.0.0
Requires-Dist: nonebot_adapter_onebot>=2.3.1
Requires-Dist: nonebot_adapter_qq>=1.3.5
Requires-Dist: nonebot_plugin_htmlrender
Requires-Dist: nonebot_plugin_localstore
Project-URL: Homepage, https://github.com/nek0us/nonebot-plugin-gpt
Project-URL: Repository, https://github.com/nek0us/nonebot-plugin-gpt
